mdt69x/__init__.py
mdt69x/mdt69x.py
mdt69x-1.0.11.dist-info/LICENSE
mdt69x-1.0.11.dist-info/METADATA
mdt69x-1.0.11.dist-info/WHEEL
mdt69x-1.0.11.dist-info/top_level.txt
mdt69x-1.0.11.dist-info/RECORD
