Metadata-Version: 2.1
Name: mdt69x
Version: 1.0.11
Summary: Package to communicate with Thorlab MDT69X Piezo controller
Home-page: https://github.com/claudioarena/mdt69x
Author: Claudio Arena
Author-email: claudio.arena.12@ucl.ac.uk
Classifier: Programming Language :: Python :: 3
Classifier: License :: OSI Approved :: MIT License
Classifier: Operating System :: OS Independent
Requires-Python: >=3.6
License-File: LICENSE
Requires-Dist: markdown
Requires-Dist: pyserial
